{
	"textures": [
		{
			"image": "bullet.png",
			"format": "RGBA8888",
			"size": {
				"w": 88,
				"h": 147
			},
			"scale": 1,
			"frames": [
				{
					"filename": "blullet-1.png",
					"rotated": false,
					"trimmed": true,
					"sourceSize": {
						"w": 90,
						"h": 40
					},
					"spriteSourceSize": {
						"x": 3,
						"y": 2,
						"w": 86,
						"h": 35
					},
					"frame": {
						"x": 1,
						"y": 1,
						"w": 86,
						"h": 35
					}
				},
				{
					"filename": "blullet-2.png",
					"rotated": false,
					"trimmed": true,
					"sourceSize": {
						"w": 90,
						"h": 40
					},
					"spriteSourceSize": {
						"x": 10,
						"y": 0,
						"w": 80,
						"h": 40
					},
					"frame": {
						"x": 1,
						"y": 38,
						"w": 80,
						"h": 40
					}
				},
				{
					"filename": "blullet-3.png",
					"rotated": false,
					"trimmed": true,
					"sourceSize": {
						"w": 90,
						"h": 40
					},
					"spriteSourceSize": {
						"x": 13,
						"y": 5,
						"w": 74,
						"h": 29
					},
					"frame": {
						"x": 1,
						"y": 80,
						"w": 74,
						"h": 29
					}
				},
				{
					"filename": "blullet-0.png",
					"rotated": false,
					"trimmed": true,
					"sourceSize": {
						"w": 90,
						"h": 40
					},
					"spriteSourceSize": {
						"x": 16,
						"y": 3,
						"w": 71,
						"h": 35
					},
					"frame": {
						"x": 1,
						"y": 111,
						"w": 71,
						"h": 35
					}
				}
			]
		}
	],
	"meta": {
		"app": "https://www.codeandweb.com/texturepacker",
		"version": "3.0",
		"smartupdate": "$TexturePacker:SmartUpdate:002cc31fa90fb3a027b3052a69a5ebe5:178dc881ee328fe9bec496a33c74b901:ce0aeb6b1dd09bd42d31ec6c01e81ef2$"
	}
}
